<?xml version="1.0" encoding="utf-8"?>
<!DOCTYPE hibernate-mapping PUBLIC "-//Hibernate/Hibernate Mapping DTD 3.0//EN"
"http://hibernate.sourceforge.net/hibernate-mapping-3.0.dtd">
<!-- 
    Mapping file autogenerated by MyEclipse Persistence Tools
-->
<hibernate-mapping>
    <class name="com.hr.pojo.SalChance" table="sal_chance" catalog="crm">
        <id name="chcId" type="java.lang.Integer">
            <column name="chc_id" />
            <generator class="identity"></generator>
        </id>
        <property name="chcSource" type="java.lang.String">
            <column name="chc_source" length="100" />
        </property>
        <property name="chcCustName" type="java.lang.String">
            <column name="chc_cust_name" length="200" />
        </property>
        <property name="chcTitle" type="java.lang.String">
            <column name="chc_title" length="400" />
        </property>
        <property name="chcRate" type="java.lang.Integer">
            <column name="chc_rate" />
        </property>
        <property name="chcLinkman" type="java.lang.String">
            <column name="chc_linkman" length="100" />
        </property>
        <property name="chcTel" type="java.lang.String">
            <column name="chc_tel" length="100" />
        </property>
        <property name="chcDesc" type="java.lang.String">
            <column name="chc_desc" length="2000" />
        </property>
       
        <property name="chcCreateId" type="java.lang.Integer">
            <column name="chc_create_id" />
        </property>
         
        <property name="chcCreateBy" type="java.lang.String">
            <column name="chc_create_by" length="100" />
        </property>
        <property name="chcCreateDate" type="java.sql.Timestamp">
            <column name="chc_create_date" length="19" />
        </property>
        <!--<property name="chcDueId" type="java.lang.Integer">
            <column name="chc_due_id" />
        </property>
        --><property name="chcDueTo" type="java.lang.String">
            <column name="chc_due_to" length="100" />
        </property>
        <property name="chcDueDate" type="java.sql.Timestamp">
            <column name="chc_due_date" length="19" />
        </property>
        <property name="chcStatus" type="java.lang.String">
            <column name="chc_status" length="1" />
        </property>
        <bag inverse="true" name="sp" cascade="all" >
        <key column="pla_chc_id"></key>
        <one-to-many class="com.hr.pojo.SalPlan"/>
        </bag>
        <many-to-one name="su" cascade="all" column="chc_due_id" class="com.hr.pojo.SysUser"></many-to-one>
    
    </class>
</hibernate-mapping>
